{
  "last_run": "2026-07-23T00:04:16.568200",
  "feeds_checked": {
    "https://techcrunch.com/category/artificial-intelligence/feed/": "2026-07-23T00:04:14.350933",
    "https://tomtunguz.com/index.xml": "2026-07-23T00:04:14.331494",
    "https://simonwillison.net/atom/everything/": "2026-07-23T00:04:14.955557",
    "https://future.com/feed/": "2026-07-23T00:04:14.255044",
    "https://garymarcus.substack.com/feed": "2026-07-07T00:58:59.779004",
    "https://lastweekin.ai/feed": "2026-07-23T00:04:15.530696",
    "https://importai.substack.com/feed": "2026-07-07T00:58:59.709317",
    "https://www.interconnects.ai/feed": "2026-07-23T00:04:14.886743",
    "https://www.technologyreview.com/topic/artificial-intelligence/feed/": "2026-07-23T00:04:14.980577",
    "https://www.latent.space/feed": "2026-07-23T00:04:15.177656",
    "https://www.theverge.com/rss/ai-artificial-intelligence/index.xml": "2026-07-23T00:04:14.365183",
    "https://venturebeat.com/category/ai/feed/": "2026-07-23T00:04:15.200122",
    "https://huggingface.co/blog/feed.xml": "2026-07-23T00:04:15.442169",
    "https://magazine.sebastianraschka.com/feed": "2026-07-23T00:04:16.209189",
    "https://www.oneusefulthing.org/feed": "2026-07-23T00:04:15.739897",
    "https://blog.eladgil.com/feed": "2026-07-23T00:04:14.785338",
    "https://www.sequoiacap.com/feed/": "2026-07-23T00:04:15.302774",
    "https://www.aisnakeoil.com/feed": "2026-07-23T00:04:16.546927",
    "https://arstechnica.com/ai/feed/": "2026-07-23T00:04:15.556573",
    "https://the-decoder.com/feed/": "2026-07-23T00:04:16.556458",
    "https://menlovc.com/feed/": "2026-07-23T00:04:14.512522",
    "https://www.saastr.com/feed/": "2026-07-23T00:04:15.478866",
    "https://www.insightpartners.com/feed/": "2026-07-07T00:58:59.377094",
    "https://press.airstreet.com/feed": "2026-07-23T00:04:14.469650",
    "https://foundersfund.com/feed/": "2026-07-23T00:04:15.247479",
    "https://sarahtavel.substack.com/feed": "2026-07-07T00:59:00.136379",
    "https://www.radical.vc/feed/": "2026-07-23T00:04:16.246772"
  },
  "signals_generated": 1039
}