{
  "last_run": "2026-07-12T02:25:02.084505",
  "feeds_checked": {
    "https://techcrunch.com/category/artificial-intelligence/feed/": "2026-07-12T02:24:59.697300",
    "https://tomtunguz.com/index.xml": "2026-07-12T02:24:59.612321",
    "https://simonwillison.net/atom/everything/": "2026-07-12T02:25:00.055674",
    "https://future.com/feed/": "2026-07-12T02:24:59.580977",
    "https://garymarcus.substack.com/feed": "2026-07-07T00:58:59.779004",
    "https://lastweekin.ai/feed": "2026-07-12T02:25:01.511046",
    "https://importai.substack.com/feed": "2026-07-07T00:58:59.709317",
    "https://www.interconnects.ai/feed": "2026-07-12T02:24:59.965494",
    "https://www.technologyreview.com/topic/artificial-intelligence/feed/": "2026-07-12T02:25:00.499286",
    "https://www.latent.space/feed": "2026-07-12T02:25:00.475522",
    "https://www.theverge.com/rss/ai-artificial-intelligence/index.xml": "2026-07-12T02:25:00.510803",
    "https://venturebeat.com/category/ai/feed/": "2026-07-12T02:25:00.901709",
    "https://huggingface.co/blog/feed.xml": "2026-07-12T02:25:00.644695",
    "https://magazine.sebastianraschka.com/feed": "2026-07-12T02:25:01.373162",
    "https://www.oneusefulthing.org/feed": "2026-07-12T02:25:00.803162",
    "https://blog.eladgil.com/feed": "2026-07-12T02:25:00.325314",
    "https://www.sequoiacap.com/feed/": "2026-07-12T02:25:01.465485",
    "https://www.aisnakeoil.com/feed": "2026-07-12T02:25:01.867459",
    "https://arstechnica.com/ai/feed/": "2026-07-12T02:25:01.544452",
    "https://the-decoder.com/feed/": "2026-07-12T02:25:02.076511",
    "https://menlovc.com/feed/": "2026-07-12T02:24:59.997454",
    "https://www.saastr.com/feed/": "2026-07-12T02:24:59.752971",
    "https://www.insightpartners.com/feed/": "2026-07-07T00:58:59.377094",
    "https://press.airstreet.com/feed": "2026-07-12T02:24:59.875403",
    "https://foundersfund.com/feed/": "2026-07-12T02:25:00.841694",
    "https://sarahtavel.substack.com/feed": "2026-07-07T00:59:00.136379",
    "https://www.radical.vc/feed/": "2026-07-12T02:25:01.520005"
  },
  "signals_generated": 698
}