{
  "last_run": "2026-07-17T05:39:26.792346",
  "feeds_checked": {
    "https://techcrunch.com/category/artificial-intelligence/feed/": "2026-07-17T05:39:24.300643",
    "https://tomtunguz.com/index.xml": "2026-07-17T05:39:23.725892",
    "https://simonwillison.net/atom/everything/": "2026-07-17T05:39:24.357877",
    "https://future.com/feed/": "2026-07-17T05:39:23.816013",
    "https://garymarcus.substack.com/feed": "2026-07-07T00:58:59.779004",
    "https://lastweekin.ai/feed": "2026-07-17T05:39:24.191938",
    "https://importai.substack.com/feed": "2026-07-07T00:58:59.709317",
    "https://www.interconnects.ai/feed": "2026-07-17T05:39:24.851355",
    "https://www.technologyreview.com/topic/artificial-intelligence/feed/": "2026-07-17T05:39:24.226809",
    "https://www.latent.space/feed": "2026-07-17T05:39:24.085831",
    "https://www.theverge.com/rss/ai-artificial-intelligence/index.xml": "2026-07-17T05:39:24.110835",
    "https://venturebeat.com/category/ai/feed/": "2026-07-17T05:39:24.385204",
    "https://huggingface.co/blog/feed.xml": "2026-07-17T05:39:24.546336",
    "https://magazine.sebastianraschka.com/feed": "2026-07-17T05:39:25.455882",
    "https://www.oneusefulthing.org/feed": "2026-07-17T05:39:24.745305",
    "https://blog.eladgil.com/feed": "2026-07-17T05:39:23.688437",
    "https://www.sequoiacap.com/feed/": "2026-07-17T05:39:24.289813",
    "https://www.aisnakeoil.com/feed": "2026-07-17T05:39:25.896639",
    "https://arstechnica.com/ai/feed/": "2026-07-17T05:39:26.149486",
    "https://the-decoder.com/feed/": "2026-07-17T05:39:26.781497",
    "https://menlovc.com/feed/": "2026-07-17T05:39:23.857537",
    "https://www.saastr.com/feed/": "2026-07-17T05:39:25.499238",
    "https://www.insightpartners.com/feed/": "2026-07-07T00:58:59.377094",
    "https://press.airstreet.com/feed": "2026-07-17T05:39:23.359294",
    "https://foundersfund.com/feed/": "2026-07-17T05:39:24.898225",
    "https://sarahtavel.substack.com/feed": "2026-07-07T00:59:00.136379",
    "https://www.radical.vc/feed/": "2026-07-17T05:39:25.558656"
  },
  "signals_generated": 887
}