{
  "last_run": "2026-07-18T15:53:30.622567",
  "feeds_checked": {
    "https://www.reddit.com/r/cybersecurity/.rss": "2026-07-18T15:52:58.441315",
    "https://www.reddit.com/r/netsec/.rss": "2026-07-18T15:53:00.233500",
    "https://techcrunch.com/author/zack-whittaker/feed/": "2026-07-18T15:53:00.756849",
    "https://techcrunch.com/category/startups/feed/": "2026-07-18T15:53:00.747391",
    "https://techcrunch.com/category/security/feed/": "2026-07-18T15:53:00.601414",
    "https://techcrunch.com/author/lorenzo-franceschi-bicchierai/feed/": "2026-07-18T15:53:00.736473",
    "https://www.schneier.com/feed/": "2026-07-18T15:53:00.989939",
    "https://feeds.twit.tv/sn.xml": "2026-07-18T15:53:01.563695",
    "https://www.wired.com/feed/category/security/latest/rss": "2026-07-18T15:53:00.947438",
    "https://sequoiacap.com/feed/": "2026-07-18T15:53:00.388683",
    "https://news.ycombinator.com/rss": "2026-07-18T15:53:02.601444",
    "https://www.helpnetsecurity.com/feed/": "2026-07-18T15:53:01.577321",
    "https://www.youtube.com/feeds/videos.xml?channel_id=UCVeW9qkBjo3zosnqUbG7CFw": "2026-07-18T15:53:01.257498",
    "https://sed-cms.broadcom.com/rss/v1/blogs/rss.xml": "2026-07-07T00:58:26.244161",
    "https://www.cisecurity.org/feed/advisories": "2026-07-18T15:53:02.762700",
    "https://www.schneier.com/blog/atom.xml": "2026-07-18T15:53:01.015082",
    "https://www.malwaretech.com/feed": "2026-07-18T15:53:01.271487",
    "https://www.nist.gov/blogs/cybersecurity-insights/rss.xml": "2026-07-18T15:53:01.811943",
    "https://ventureinsecurity.net/feed": "2026-07-18T15:53:04.845141",
    "https://risky.biz/feeds/risky-business/": "2026-07-18T15:53:03.852344",
    "https://www.troyhunt.com/rss/": "2026-07-18T15:53:04.064970",
    "https://ballisticventures.com/feed/": "2026-07-18T15:53:00.808384",
    "https://www.eff.org/rss/updates.xml": "2026-07-18T15:53:01.794461",
    "https://www.zetter-zeroday.com/feed/": "2026-07-18T15:53:02.050008",
    "https://news.crunchbase.com/feed/": "2026-07-18T15:53:01.357805",
    "https://www.producthunt.com/feed": "2026-07-18T15:53:01.311597",
    "http://feeds.feedburner.com/govtech/blogs/lohrmann_on_infrastructure": "2026-07-18T15:53:02.741216",
    "https://grahamcluley.com/feed/": "2026-07-18T15:53:01.371425",
    "https://krebsonsecurity.com/feed/": "2026-07-18T15:53:00.893573",
    "https://medium.com/feed/tag/cybersecurity": "2026-07-18T15:53:00.400834",
    "https://redcanary.com/blog/feed/": "2026-07-18T15:53:01.320225",
    "https://perspectives.acrewcapital.com/feed": "2026-07-18T15:53:00.716365",
    "https://feeds.feedburner.com/TheHackersNews": "2026-07-18T15:53:01.195352",
    "https://feeds.feedburner.com/TroyHunt": "2026-07-18T15:53:01.243458",
    "https://nao-sec.org/feed": "2026-07-18T15:53:02.393793",
    "https://isc.sans.edu/rssfeed_full.xml": "2026-07-18T15:53:02.200302",
    "https://www.youtube.com/feeds/videos.xml?channel_id=UC0ArlFuFYMpEewyRBzdLHiw": "2026-07-18T15:53:01.209766",
    "https://raincapital.substack.com/feed": "2026-07-07T00:58:26.857320",
    "https://www.theguardian.com/technology/data-computer-security/rss": "2026-07-18T15:53:01.864980",
    "https://www.bitdefender.com/blog/api/rss/labs/": "2026-07-18T15:53:04.209301",
    "https://www.bellingcat.com/feed/": "2026-07-18T15:53:01.987901",
    "https://medium.com/feed/@sebdraven": "2026-07-18T15:53:00.425299",
    "https://medium.com/feed/lightspeed-venture-partners": "2026-07-18T15:53:00.478786",
    "https://www.globenewswire.com/RssFeed/subjectcode/35-Technology/feedTitle/GlobeNewswire%20-%20Technology": "2026-07-18T15:53:02.426194",
    "https://medium.com/feed/anton-on-security": "2026-07-18T15:53:00.540799",
    "https://www.grahamcluley.com/feed/": "2026-07-18T15:53:02.788781",
    "https://therecord.media/feed/": "2026-07-18T15:53:01.463183",
    "https://medium.com/feed/tag/infosec": "2026-07-18T15:53:00.772460",
    "https://danielmiessler.com/feed/": "2026-07-18T15:53:03.606309",
    "https://arstechnica.com/tag/security/feed/": "2026-07-18T15:53:01.400033",
    "https://arstechnica.com/author/dan-goodin/feed/": "2026-07-18T15:53:01.427933",
    "http://www.malware-traffic-analysis.net/blog-entries.rss": "2026-07-18T15:53:06.245924",
    "https://www.prnewswire.com/rss/information-technology-latest-news/information-technology-latest-news-list.rss": "2026-07-18T15:53:01.840577",
    "https://www.zdnet.com/topic/security/rss.xml": "2026-07-18T15:53:04.218924",
    "https://www.proofpoint.com/us/rss.xml": "2026-07-18T15:53:04.031160",
    "https://www.upguard.com/news/rss.xml": "2026-07-18T15:53:04.719066",
    "https://feeds.megaphone.fm/darknetdiaries": "2026-07-18T15:53:05.581521",
    "https://sensepost.com/rss.xml": "2026-07-18T15:53:05.216095",
    "https://research.checkpoint.com/feed/": "2026-07-18T15:53:04.667654",
    "https://blog.cloudflare.com/tag/security/rss": "2026-07-18T15:53:04.197391",
    "https://blog.eclecticiq.com/rss.xml": "2026-07-18T15:53:04.914725",
    "https://blog.0patch.com/feeds/posts/default": "2026-07-18T11:57:55.155431",
    "https://feeds.feedburner.com/securityweek": "2026-07-18T15:53:06.083889",
    "https://www.sentinelone.com/labs/feed/": "2026-07-18T15:53:05.672370",
    "http://www.techrepublic.com/rssfeeds/topic/security/?feedType=rssfeeds": "2026-07-18T15:53:07.395451",
    "https://blog.fox-it.com/feed/": "2026-07-18T15:53:05.912634",
    "https://blog.qualys.com/feed": "2026-07-18T15:53:03.989164",
    "https://blog.virustotal.com/feeds/posts/default": "2026-07-18T15:53:06.237809",
    "http://feeds.trendmicro.com/TrendMicroSimplySecurity": "2026-07-18T15:53:04.531008",
    "https://us-cert.cisa.gov/ics/advisories/advisories.xml": "2026-07-07T00:58:27.138544",
    "https://threatpost.com/feed/": "2026-07-18T15:53:04.039849",
    "https://medium.com/feed/@edsim": "2026-07-18T15:53:01.490885",
    "http://feeds.feedburner.com/feedburner/Talos": "2026-07-18T15:53:02.736171",
    "https://www.upguard.com/breaches/rss.xml": "2026-07-18T15:53:06.073879",
    "http://www.infosecurity-magazine.com/rss/news/": "2026-07-18T15:53:07.361610",
    "https://cofense.com/feed/": "2026-07-18T15:53:04.900885",
    "https://www.hackread.com/feed/": "2026-07-18T15:53:07.377614",
    "https://www.microsoft.com/security/blog/feed/": "2026-07-18T15:53:06.341326",
    "https://www.virusbulletin.com/rss": "2026-07-18T15:53:04.502920",
    "http://www.darknet.org.uk/feed/": "2026-07-18T14:48:16.696495",
    "https://blogs.cisco.com/security/feed": "2026-07-18T15:53:06.392944",
    "https://blog.malwarebytes.com/feed/": "2026-07-18T15:53:06.504280",
    "https://us-cert.cisa.gov/ncas/alerts.xml": "2026-07-07T00:58:28.263222",
    "https://danielmiessler.com/feed": "2026-07-18T15:53:07.304993",
    "https://www.smashingsecurity.com/rss": "2026-07-18T15:53:12.606031",
    "http://securityaffairs.co/wordpress/feed": "2026-07-18T15:53:08.504941",
    "https://googleonlinesecurity.blogspot.com/atom.xml": "2026-07-18T15:53:07.870590",
    "https://securelist.com/feed/": "2026-07-18T15:53:06.054476",
    "https://www.paloaltonetworks.com/blog/rss": "2026-07-18T15:53:06.383495",
    "https://us-cert.cisa.gov/ncas/analysis-reports.xml": "2026-07-07T00:58:30.460486",
    "https://blog.quarkslab.com/feeds/all.rss.xml": "2026-07-18T15:53:08.468664",
    "https://us-cert.cisa.gov/ncas/current-activity.xml": "2026-07-07T00:58:30.650592",
    "https://googleprojectzero.blogspot.com/feeds/posts/default": "2026-07-18T15:53:14.393156",
    "https://socprime.com/blog/feed/": "2026-07-18T15:53:07.450187",
    "https://risky.biz/feeds/risky-business-news/": "2026-07-18T15:53:14.613287",
    "https://tldrsec.com/feed.xml": "2026-07-18T15:53:15.148451",
    "http://eset.com/int/rss.xml": "2026-07-18T15:53:08.512028"
  },
  "signals_generated": 5415
}