{
  "last_run": "2026-07-12T05:54:19.043341",
  "feeds_checked": {
    "https://www.reddit.com/r/cybersecurity/.rss": "2026-07-12T05:53:46.755874",
    "https://www.reddit.com/r/netsec/.rss": "2026-07-12T05:53:48.400653",
    "https://techcrunch.com/author/zack-whittaker/feed/": "2026-07-12T05:53:49.074225",
    "https://techcrunch.com/category/startups/feed/": "2026-07-12T05:53:48.828257",
    "https://techcrunch.com/category/security/feed/": "2026-07-12T05:53:49.165296",
    "https://techcrunch.com/author/lorenzo-franceschi-bicchierai/feed/": "2026-07-12T05:53:49.223667",
    "https://www.schneier.com/feed/": "2026-07-12T05:53:49.245125",
    "https://feeds.twit.tv/sn.xml": "2026-07-12T05:53:49.764592",
    "https://www.wired.com/feed/category/security/latest/rss": "2026-07-12T05:53:49.508020",
    "https://sequoiacap.com/feed/": "2026-07-12T05:53:48.887222",
    "https://news.ycombinator.com/rss": "2026-07-12T05:53:52.936770",
    "https://www.helpnetsecurity.com/feed/": "2026-07-12T05:53:49.778134",
    "https://www.youtube.com/feeds/videos.xml?channel_id=UCVeW9qkBjo3zosnqUbG7CFw": "2026-07-12T05:53:49.550872",
    "https://sed-cms.broadcom.com/rss/v1/blogs/rss.xml": "2026-07-07T00:58:26.244161",
    "https://www.cisecurity.org/feed/advisories": "2026-07-12T05:53:50.324543",
    "https://www.schneier.com/blog/atom.xml": "2026-07-12T02:24:28.348011",
    "https://www.malwaretech.com/feed": "2026-07-12T05:53:49.828987",
    "https://www.nist.gov/blogs/cybersecurity-insights/rss.xml": "2026-07-12T05:53:50.245133",
    "https://ventureinsecurity.net/feed": "2026-07-12T05:53:54.846349",
    "https://risky.biz/feeds/risky-business/": "2026-07-12T05:53:53.755876",
    "https://www.troyhunt.com/rss/": "2026-07-12T05:53:52.043457",
    "https://ballisticventures.com/feed/": "2026-07-12T05:53:48.939612",
    "https://www.eff.org/rss/updates.xml": "2026-07-12T05:53:52.547975",
    "https://www.zetter-zeroday.com/feed/": "2026-07-12T05:53:50.552123",
    "https://news.crunchbase.com/feed/": "2026-07-12T05:53:50.222862",
    "https://www.producthunt.com/feed": "2026-07-12T05:53:50.172637",
    "http://feeds.feedburner.com/govtech/blogs/lohrmann_on_infrastructure": "2026-07-12T05:53:50.330185",
    "https://grahamcluley.com/feed/": "2026-07-12T05:53:50.138555",
    "https://krebsonsecurity.com/feed/": "2026-07-12T05:53:49.492762",
    "https://medium.com/feed/tag/cybersecurity": "2026-07-12T05:53:48.574507",
    "https://redcanary.com/blog/feed/": "2026-07-12T05:53:49.785380",
    "https://perspectives.acrewcapital.com/feed": "2026-07-12T05:53:49.045296",
    "https://feeds.feedburner.com/TheHackersNews": "2026-07-12T05:53:49.133591",
    "https://feeds.feedburner.com/TroyHunt": "2026-07-12T05:53:49.202394",
    "https://nao-sec.org/feed": "2026-07-12T05:53:50.105566",
    "https://isc.sans.edu/rssfeed_full.xml": "2026-07-12T05:53:50.411044",
    "https://www.youtube.com/feeds/videos.xml?channel_id=UC0ArlFuFYMpEewyRBzdLHiw": "2026-07-12T05:53:49.524506",
    "https://raincapital.substack.com/feed": "2026-07-07T00:58:26.857320",
    "https://www.theguardian.com/technology/data-computer-security/rss": "2026-07-12T05:53:50.360262",
    "https://www.bitdefender.com/blog/api/rss/labs/": "2026-07-12T05:53:52.556385",
    "https://www.bellingcat.com/feed/": "2026-07-12T05:53:52.312494",
    "https://medium.com/feed/@sebdraven": "2026-07-12T05:53:48.605214",
    "https://medium.com/feed/lightspeed-venture-partners": "2026-07-12T05:53:48.739163",
    "https://www.globenewswire.com/RssFeed/subjectcode/35-Technology/feedTitle/GlobeNewswire%20-%20Technology": "2026-07-12T05:53:49.867369",
    "https://medium.com/feed/anton-on-security": "2026-07-12T05:53:48.680937",
    "https://www.grahamcluley.com/feed/": "2026-07-12T05:53:52.163708",
    "https://therecord.media/feed/": "2026-07-11T23:51:33.893184",
    "https://medium.com/feed/tag/infosec": "2026-07-12T05:53:48.760576",
    "https://danielmiessler.com/feed/": "2026-07-12T05:53:51.442915",
    "https://arstechnica.com/tag/security/feed/": "2026-07-12T05:53:49.634110",
    "https://arstechnica.com/author/dan-goodin/feed/": "2026-07-12T05:53:49.668505",
    "http://www.malware-traffic-analysis.net/blog-entries.rss": "2026-07-12T05:53:54.922983",
    "https://www.prnewswire.com/rss/information-technology-latest-news/information-technology-latest-news-list.rss": "2026-07-12T05:53:54.675284",
    "https://www.zdnet.com/topic/security/rss.xml": "2026-07-12T05:53:52.171750",
    "https://www.proofpoint.com/us/rss.xml": "2026-07-12T05:53:54.443321",
    "https://www.upguard.com/news/rss.xml": "2026-07-12T05:53:54.423087",
    "https://feeds.megaphone.fm/darknetdiaries": "2026-07-12T05:53:54.385248",
    "https://sensepost.com/rss.xml": "2026-07-12T05:53:52.923933",
    "https://research.checkpoint.com/feed/": "2026-07-12T05:53:52.017477",
    "https://blog.cloudflare.com/tag/security/rss": "2026-07-12T05:53:53.099622",
    "https://blog.eclecticiq.com/rss.xml": "2026-07-12T05:53:54.438526",
    "https://blog.0patch.com/feeds/posts/default": "2026-07-12T05:53:54.885044",
    "https://feeds.feedburner.com/securityweek": "2026-07-12T05:53:54.452706",
    "https://www.sentinelone.com/labs/feed/": "2026-07-12T05:53:52.146543",
    "http://www.techrepublic.com/rssfeeds/topic/security/?feedType=rssfeeds": "2026-07-12T05:53:54.913311",
    "https://blog.fox-it.com/feed/": "2026-07-12T05:53:51.863814",
    "https://blog.qualys.com/feed": "2026-07-12T05:53:53.930040",
    "https://blog.virustotal.com/feeds/posts/default": "2026-07-12T05:53:54.642045",
    "http://feeds.trendmicro.com/TrendMicroSimplySecurity": "2026-07-12T05:53:50.392443",
    "https://us-cert.cisa.gov/ics/advisories/advisories.xml": "2026-07-07T00:58:27.138544",
    "https://threatpost.com/feed/": "2026-07-12T05:53:52.180827",
    "https://medium.com/feed/@edsim": "2026-07-12T05:53:49.108594",
    "http://feeds.feedburner.com/feedburner/Talos": "2026-07-12T05:53:50.501280",
    "https://www.upguard.com/breaches/rss.xml": "2026-07-12T05:53:54.700243",
    "http://www.infosecurity-magazine.com/rss/news/": "2026-07-12T05:53:55.457587",
    "https://cofense.com/feed/": "2026-07-12T05:53:53.840195",
    "https://www.hackread.com/feed/": "2026-07-12T05:53:55.388567",
    "https://www.microsoft.com/security/blog/feed/": "2026-07-12T05:53:53.185642",
    "https://www.virusbulletin.com/rss": "2026-07-12T05:53:52.318754",
    "http://www.darknet.org.uk/feed/": "2026-07-12T05:53:54.929101",
    "https://blogs.cisco.com/security/feed": "2026-07-12T05:53:52.579136",
    "https://blog.malwarebytes.com/feed/": "2026-07-12T05:53:56.880552",
    "https://us-cert.cisa.gov/ncas/alerts.xml": "2026-07-07T00:58:28.263222",
    "https://danielmiessler.com/feed": "2026-07-12T05:53:56.560964",
    "https://www.smashingsecurity.com/rss": "2026-07-12T05:54:01.641811",
    "http://securityaffairs.co/wordpress/feed": "2026-07-12T05:53:55.667780",
    "https://googleonlinesecurity.blogspot.com/atom.xml": "2026-07-12T05:53:56.738398",
    "https://securelist.com/feed/": "2026-07-12T05:53:55.378677",
    "https://www.paloaltonetworks.com/blog/rss": "2026-07-12T05:53:56.787612",
    "https://us-cert.cisa.gov/ncas/analysis-reports.xml": "2026-07-07T00:58:30.460486",
    "https://blog.quarkslab.com/feeds/all.rss.xml": "2026-07-12T05:54:03.567723",
    "https://us-cert.cisa.gov/ncas/current-activity.xml": "2026-07-07T00:58:30.650592",
    "https://googleprojectzero.blogspot.com/feeds/posts/default": "2026-07-12T05:54:02.911906",
    "https://socprime.com/blog/feed/": "2026-07-12T05:53:55.623211",
    "https://risky.biz/feeds/risky-business-news/": "2026-07-12T05:54:04.248521",
    "https://tldrsec.com/feed.xml": "2026-07-12T05:54:04.830729",
    "http://eset.com/int/rss.xml": "2026-07-12T05:54:01.660695"
  },
  "signals_generated": 3168
}