{
  "last_run": "2026-07-08T20:18:30.306629",
  "feeds_checked": {
    "https://www.reddit.com/r/cybersecurity/.rss": "2026-07-08T20:17:57.790561",
    "https://www.reddit.com/r/netsec/.rss": "2026-07-08T20:17:59.637181",
    "https://techcrunch.com/author/zack-whittaker/feed/": "2026-07-08T20:18:00.213031",
    "https://techcrunch.com/category/startups/feed/": "2026-07-08T20:18:00.246637",
    "https://techcrunch.com/category/security/feed/": "2026-07-08T20:18:00.226453",
    "https://techcrunch.com/author/lorenzo-franceschi-bicchierai/feed/": "2026-07-08T20:18:01.444056",
    "https://www.schneier.com/feed/": "2026-07-08T20:18:00.825042",
    "https://feeds.twit.tv/sn.xml": "2026-07-08T20:18:00.476330",
    "https://www.wired.com/feed/category/security/latest/rss": "2026-07-08T20:18:00.309855",
    "https://sequoiacap.com/feed/": "2026-07-08T20:17:59.811349",
    "https://news.ycombinator.com/rss": "2026-07-08T20:18:02.522623",
    "https://www.helpnetsecurity.com/feed/": "2026-07-08T20:18:00.648034",
    "https://www.youtube.com/feeds/videos.xml?channel_id=UCVeW9qkBjo3zosnqUbG7CFw": "2026-07-08T20:18:01.396483",
    "https://sed-cms.broadcom.com/rss/v1/blogs/rss.xml": "2026-07-07T00:58:26.244161",
    "https://www.cisecurity.org/feed/advisories": "2026-07-08T20:18:02.597989",
    "https://www.schneier.com/blog/atom.xml": "2026-07-08T20:18:00.845328",
    "https://www.malwaretech.com/feed": "2026-07-08T20:18:01.509419",
    "https://www.nist.gov/blogs/cybersecurity-insights/rss.xml": "2026-07-08T20:18:02.716248",
    "https://ventureinsecurity.net/feed": "2026-07-08T20:18:04.155059",
    "https://risky.biz/feeds/risky-business/": "2026-07-08T20:18:01.166065",
    "https://www.troyhunt.com/rss/": "2026-07-08T20:18:03.281964",
    "https://ballisticventures.com/feed/": "2026-07-08T20:18:00.058902",
    "https://www.eff.org/rss/updates.xml": "2026-07-08T20:18:01.383358",
    "https://www.zetter-zeroday.com/feed/": "2026-07-08T20:18:01.495513",
    "https://news.crunchbase.com/feed/": "2026-07-08T20:18:00.707064",
    "https://www.producthunt.com/feed": "2026-07-08T20:18:02.574127",
    "http://feeds.feedburner.com/govtech/blogs/lohrmann_on_infrastructure": "2026-07-08T20:18:02.661601",
    "https://grahamcluley.com/feed/": "2026-07-08T20:18:00.766798",
    "https://krebsonsecurity.com/feed/": "2026-07-08T20:18:00.808349",
    "https://medium.com/feed/tag/cybersecurity": "2026-07-08T20:17:59.860273",
    "https://redcanary.com/blog/feed/": "2026-07-08T20:18:01.517310",
    "https://perspectives.acrewcapital.com/feed": "2026-07-08T20:18:00.171273",
    "https://feeds.feedburner.com/TheHackersNews": "2026-07-08T20:18:01.631632",
    "https://feeds.feedburner.com/TroyHunt": "2026-07-08T20:18:01.612037",
    "https://nao-sec.org/feed": "2026-07-08T20:18:02.942302",
    "https://isc.sans.edu/rssfeed_full.xml": "2026-07-08T20:18:03.162803",
    "https://www.youtube.com/feeds/videos.xml?channel_id=UC0ArlFuFYMpEewyRBzdLHiw": "2026-07-08T20:18:01.412841",
    "https://raincapital.substack.com/feed": "2026-07-07T00:58:26.857320",
    "https://www.theguardian.com/technology/data-computer-security/rss": "2026-07-08T20:18:03.140732",
    "https://www.bitdefender.com/blog/api/rss/labs/": "2026-07-08T20:18:05.166551",
    "https://www.bellingcat.com/feed/": "2026-07-08T20:18:03.111379",
    "https://medium.com/feed/@sebdraven": "2026-07-08T20:17:59.841340",
    "https://medium.com/feed/lightspeed-venture-partners": "2026-07-08T20:17:59.938085",
    "https://www.globenewswire.com/RssFeed/subjectcode/35-Technology/feedTitle/GlobeNewswire%20-%20Technology": "2026-07-08T20:18:01.429671",
    "https://medium.com/feed/anton-on-security": "2026-07-08T20:18:00.013743",
    "https://www.grahamcluley.com/feed/": "2026-07-08T20:18:03.621814",
    "https://therecord.media/feed/": "2026-07-08T20:18:01.672918",
    "https://medium.com/feed/tag/infosec": "2026-07-08T20:18:00.294566",
    "https://danielmiessler.com/feed/": "2026-07-08T20:18:02.510697",
    "https://arstechnica.com/tag/security/feed/": "2026-07-08T20:18:01.566530",
    "https://arstechnica.com/author/dan-goodin/feed/": "2026-07-08T20:18:02.656081",
    "http://www.malware-traffic-analysis.net/blog-entries.rss": "2026-07-08T20:18:06.671655",
    "https://www.prnewswire.com/rss/information-technology-latest-news/information-technology-latest-news-list.rss": "2026-07-08T20:18:01.534956",
    "https://www.zdnet.com/topic/security/rss.xml": "2026-07-08T20:18:04.348714",
    "https://www.proofpoint.com/us/rss.xml": "2026-07-08T20:18:02.978259",
    "https://www.upguard.com/news/rss.xml": "2026-07-08T20:18:05.827538",
    "https://feeds.megaphone.fm/darknetdiaries": "2026-07-08T20:18:05.134563",
    "https://sensepost.com/rss.xml": "2026-07-08T20:18:04.708339",
    "https://research.checkpoint.com/feed/": "2026-07-08T20:18:05.344821",
    "https://blog.cloudflare.com/tag/security/rss": "2026-07-08T20:18:04.012992",
    "https://blog.eclecticiq.com/rss.xml": "2026-07-08T20:18:03.847222",
    "https://blog.0patch.com/feeds/posts/default": "2026-07-08T20:18:07.001931",
    "https://feeds.feedburner.com/securityweek": "2026-07-08T20:18:06.679962",
    "https://www.sentinelone.com/labs/feed/": "2026-07-08T20:18:03.713596",
    "http://www.techrepublic.com/rssfeeds/topic/security/?feedType=rssfeeds": "2026-07-08T20:18:07.036913",
    "https://blog.fox-it.com/feed/": "2026-07-08T20:18:03.595404",
    "https://blog.qualys.com/feed": "2026-07-08T20:18:04.252128",
    "https://blog.virustotal.com/feeds/posts/default": "2026-07-08T20:18:06.954751",
    "http://feeds.trendmicro.com/TrendMicroSimplySecurity": "2026-07-08T20:18:04.281157",
    "https://us-cert.cisa.gov/ics/advisories/advisories.xml": "2026-07-07T00:58:27.138544",
    "https://threatpost.com/feed/": "2026-07-08T20:18:05.156123",
    "https://medium.com/feed/@edsim": "2026-07-08T20:18:01.664135",
    "http://feeds.feedburner.com/feedburner/Talos": "2026-07-08T20:18:03.256658",
    "https://www.upguard.com/breaches/rss.xml": "2026-07-08T20:18:06.751915",
    "http://www.infosecurity-magazine.com/rss/news/": "2026-07-08T20:18:12.044497",
    "https://cofense.com/feed/": "2026-07-08T20:18:04.340576",
    "https://www.hackread.com/feed/": "2026-07-08T20:18:12.054988",
    "https://www.microsoft.com/security/blog/feed/": "2026-07-08T20:18:03.832626",
    "https://www.virusbulletin.com/rss": "2026-07-08T20:18:05.145932",
    "http://www.darknet.org.uk/feed/": "2026-07-08T20:18:12.102333",
    "https://blogs.cisco.com/security/feed": "2026-07-08T20:18:06.965086",
    "https://blog.malwarebytes.com/feed/": "2026-07-08T20:18:12.201472",
    "https://us-cert.cisa.gov/ncas/alerts.xml": "2026-07-07T00:58:28.263222",
    "https://danielmiessler.com/feed": "2026-07-08T20:18:06.649143",
    "https://www.smashingsecurity.com/rss": "2026-07-08T20:18:11.818953",
    "http://securityaffairs.co/wordpress/feed": "2026-07-08T20:18:12.824164",
    "https://googleonlinesecurity.blogspot.com/atom.xml": "2026-07-08T20:18:12.651581",
    "https://securelist.com/feed/": "2026-07-08T20:18:05.786333",
    "https://www.paloaltonetworks.com/blog/rss": "2026-07-08T20:18:06.728371",
    "https://us-cert.cisa.gov/ncas/analysis-reports.xml": "2026-07-07T00:58:30.460486",
    "https://blog.quarkslab.com/feeds/all.rss.xml": "2026-07-08T20:18:13.770500",
    "https://us-cert.cisa.gov/ncas/current-activity.xml": "2026-07-07T00:58:30.650592",
    "https://googleprojectzero.blogspot.com/feeds/posts/default": "2026-07-08T20:18:16.226710",
    "https://socprime.com/blog/feed/": "2026-07-08T20:18:12.095053",
    "https://risky.biz/feeds/risky-business-news/": "2026-07-08T20:18:13.893410",
    "https://tldrsec.com/feed.xml": "2026-07-08T20:18:15.045475",
    "http://eset.com/int/rss.xml": "2026-07-08T20:18:12.112811"
  },
  "signals_generated": 2219
}