{
  "generated": "2026-07-21T23:54:22Z",
  "source": "SEC EDGAR Form D (getcurrent feed)",
  "count": 47,
  "signals": [
    {
      "person_name": "HII Perplexity-08, a Series of HII Perplexity-B, LLC",
      "firm": "SEC Form D",
      "signal_type": "hard",
      "signal_category": "dry_powder",
      "summary": "HII Perplexity-08, a Series of HII Perplexity-B, LLC filed Form D - private fund raising capital (fresh dry powder to deploy)",
      "excerpt": "SEC Form D, Item 3C private-fund exemption. Names the fund, not its portfolio deals.",
      "source_url": "https://www.sec.gov/Archives/edgar/data/2146813/000214681326000001/0002146813-26-000001-index.htm",
      "source_type": "sec-form-d",
      "source_date": "2026-07-21",
      "confidence": "high"
    },
    {
      "person_name": "Civitas Orlando, LP",
      "firm": "SEC Form D",
      "signal_type": "hard",
      "signal_category": "dry_powder",
      "summary": "Civitas Orlando, LP filed Form D - private fund raising capital (fresh dry powder to deploy)",
      "excerpt": "SEC Form D, Item 3C private-fund exemption. Names the fund, not its portfolio deals.",
      "source_url": "https://www.sec.gov/Archives/edgar/data/2145506/000131586326000543/0001315863-26-000543-index.htm",
      "source_type": "sec-form-d",
      "source_date": "2026-07-21",
      "confidence": "high"
    },
    {
      "person_name": "American Ventures Opportunity Fund LLC, Series I VAST",
      "firm": "SEC Form D",
      "signal_type": "hard",
      "signal_category": "dry_powder",
      "summary": "American Ventures Opportunity Fund LLC, Series I VAST filed Form D - private fund raising capital (fresh dry powder to deploy)",
      "excerpt": "SEC Form D, Item 3C private-fund exemption. Names the fund, not its portfolio deals.",
      "source_url": "https://www.sec.gov/Archives/edgar/data/2137304/000213730426000001/0002137304-26-000001-index.htm",
      "source_type": "sec-form-d",
      "source_date": "2026-07-21",
      "confidence": "high"
    },
    {
      "person_name": "Social Finance Impact-First Fund, L.P.",
      "firm": "SEC Form D",
      "signal_type": "hard",
      "signal_category": "dry_powder",
      "summary": "Social Finance Impact-First Fund, L.P. filed Form D - private fund raising capital (fresh dry powder to deploy)",
      "excerpt": "SEC Form D, Item 3C private-fund exemption. Names the fund, not its portfolio deals.",
      "source_url": "https://www.sec.gov/Archives/edgar/data/1975387/000197538726000004/0001975387-26-000004-index.htm",
      "source_type": "sec-form-d",
      "source_date": "2026-07-21",
      "confidence": "high"
    },
    {
      "person_name": "CenterSquare Value-Added Fund VI, L.P.",
      "firm": "SEC Form D",
      "signal_type": "hard",
      "signal_category": "dry_powder",
      "summary": "CenterSquare Value-Added Fund VI, L.P. filed Form D - private fund raising capital (fresh dry powder to deploy)",
      "excerpt": "SEC Form D, Item 3C private-fund exemption. Names the fund, not its portfolio deals.",
      "source_url": "https://www.sec.gov/Archives/edgar/data/2031370/000203137026000002/0002031370-26-000002-index.htm",
      "source_type": "sec-form-d",
      "source_date": "2026-07-21",
      "confidence": "high"
    },
    {
      "person_name": "Brookfield Hark Investment Partners II LP",
      "firm": "SEC Form D",
      "signal_type": "hard",
      "signal_category": "dry_powder",
      "summary": "Brookfield Hark Investment Partners II LP filed Form D - private fund raising capital (fresh dry powder to deploy)",
      "excerpt": "SEC Form D, Item 3C private-fund exemption. Names the fund, not its portfolio deals.",
      "source_url": "https://www.sec.gov/Archives/edgar/data/2146030/000214603026000001/0002146030-26-000001-index.htm",
      "source_type": "sec-form-d",
      "source_date": "2026-07-21",
      "confidence": "high"
    },
    {
      "person_name": "SCF Pine Ultimate Holdings LP",
      "firm": "SEC Form D",
      "signal_type": "hard",
      "signal_category": "dry_powder",
      "summary": "SCF Pine Ultimate Holdings LP filed Form D - private fund raising capital (fresh dry powder to deploy)",
      "excerpt": "SEC Form D, Item 3C private-fund exemption. Names the fund, not its portfolio deals.",
      "source_url": "https://www.sec.gov/Archives/edgar/data/2134310/000213431026000002/0002134310-26-000002-index.htm",
      "source_type": "sec-form-d",
      "source_date": "2026-07-21",
      "confidence": "high"
    },
    {
      "person_name": "PATHSTONE BUYOUT &amp; GROWTH 2026 FUND, L.P.",
      "firm": "SEC Form D",
      "signal_type": "hard",
      "signal_category": "dry_powder",
      "summary": "PATHSTONE BUYOUT &amp; GROWTH 2026 FUND, L.P. filed Form D - private fund raising capital (fresh dry powder to deploy)",
      "excerpt": "SEC Form D, Item 3C private-fund exemption. Names the fund, not its portfolio deals.",
      "source_url": "https://www.sec.gov/Archives/edgar/data/2140425/000214042526000001/0002140425-26-000001-index.htm",
      "source_type": "sec-form-d",
      "source_date": "2026-07-21",
      "confidence": "high"
    },
    {
      "person_name": "J.C. Flowers VI Special L.P.",
      "firm": "SEC Form D",
      "signal_type": "hard",
      "signal_category": "dry_powder",
      "summary": "J.C. Flowers VI Special L.P. filed Form D - private fund raising capital (fresh dry powder to deploy)",
      "excerpt": "SEC Form D, Item 3C private-fund exemption. Names the fund, not its portfolio deals.",
      "source_url": "https://www.sec.gov/Archives/edgar/data/2139236/000213923626000001/0002139236-26-000001-index.htm",
      "source_type": "sec-form-d",
      "source_date": "2026-07-21",
      "confidence": "high"
    },
    {
      "person_name": "AZORA SOUTHERN EUROPE OPPORTUNITIES III S.C.A. SICAV-RAIF",
      "firm": "SEC Form D",
      "signal_type": "hard",
      "signal_category": "dry_powder",
      "summary": "AZORA SOUTHERN EUROPE OPPORTUNITIES III S.C.A. SICAV-RAIF filed Form D - private fund raising capital (fresh dry powder to deploy)",
      "excerpt": "SEC Form D, Item 3C private-fund exemption. Names the fund, not its portfolio deals.",
      "source_url": "https://www.sec.gov/Archives/edgar/data/2094418/000209441826000002/0002094418-26-000002-index.htm",
      "source_type": "sec-form-d",
      "source_date": "2026-07-21",
      "confidence": "high"
    },
    {
      "person_name": "Atlantic Chestnut III Holdings, Inc.",
      "firm": "SEC Form D",
      "signal_type": "hard",
      "signal_category": "dry_powder",
      "summary": "Atlantic Chestnut III Holdings, Inc. filed Form D - private fund raising capital (fresh dry powder to deploy)",
      "excerpt": "SEC Form D, Item 3C private-fund exemption. Names the fund, not its portfolio deals.",
      "source_url": "https://www.sec.gov/Archives/edgar/data/2142263/000214226326000001/0002142263-26-000001-index.htm",
      "source_type": "sec-form-d",
      "source_date": "2026-07-21",
      "confidence": "high"
    },
    {
      "person_name": "CGMT OP, L.P.",
      "firm": "SEC Form D",
      "signal_type": "hard",
      "signal_category": "dry_powder",
      "summary": "CGMT OP, L.P. filed Form D - private fund raising capital (fresh dry powder to deploy)",
      "excerpt": "SEC Form D, Item 3C private-fund exemption. Names the fund, not its portfolio deals.",
      "source_url": "https://www.sec.gov/Archives/edgar/data/1635445/000163544526000004/0001635445-26-000004-index.htm",
      "source_type": "sec-form-d",
      "source_date": "2026-07-21",
      "confidence": "high"
    },
    {
      "person_name": "Botero Coffee Club Fund LLC",
      "firm": "SEC Form D",
      "signal_type": "hard",
      "signal_category": "dry_powder",
      "summary": "Botero Coffee Club Fund LLC filed Form D - private fund raising capital (fresh dry powder to deploy)",
      "excerpt": "SEC Form D, Item 3C private-fund exemption. Names the fund, not its portfolio deals.",
      "source_url": "https://www.sec.gov/Archives/edgar/data/2075440/000207544026000001/0002075440-26-000001-index.htm",
      "source_type": "sec-form-d",
      "source_date": "2026-07-21",
      "confidence": "high"
    },
    {
      "person_name": "WDC X.AI, LLC",
      "firm": "SEC Form D",
      "signal_type": "hard",
      "signal_category": "dry_powder",
      "summary": "WDC X.AI, LLC filed Form D - private fund raising capital (fresh dry powder to deploy)",
      "excerpt": "SEC Form D, Item 3C private-fund exemption. Names the fund, not its portfolio deals.",
      "source_url": "https://www.sec.gov/Archives/edgar/data/2112117/000211211726000001/0002112117-26-000001-index.htm",
      "source_type": "sec-form-d",
      "source_date": "2026-07-21",
      "confidence": "high"
    },
    {
      "person_name": "UNIVERSE PRO INC",
      "firm": "SEC Form D",
      "signal_type": "hard",
      "signal_category": "dry_powder",
      "summary": "UNIVERSE PRO INC filed Form D - private fund raising capital (fresh dry powder to deploy)",
      "excerpt": "SEC Form D, Item 3C private-fund exemption. Names the fund, not its portfolio deals.",
      "source_url": "https://www.sec.gov/Archives/edgar/data/2146336/000214633626000001/0002146336-26-000001-index.htm",
      "source_type": "sec-form-d",
      "source_date": "2026-07-21",
      "confidence": "high"
    },
    {
      "person_name": "Sarissa Capital Offshore Fund Ltd",
      "firm": "SEC Form D",
      "signal_type": "hard",
      "signal_category": "dry_powder",
      "summary": "Sarissa Capital Offshore Fund Ltd filed Form D - private fund raising capital (fresh dry powder to deploy)",
      "excerpt": "SEC Form D, Item 3C private-fund exemption. Names the fund, not its portfolio deals.",
      "source_url": "https://www.sec.gov/Archives/edgar/data/1575285/000157528526000001/0001575285-26-000001-index.htm",
      "source_type": "sec-form-d",
      "source_date": "2026-07-21",
      "confidence": "high"
    },
    {
      "person_name": "J.C. Flowers VI L.P.",
      "firm": "SEC Form D",
      "signal_type": "hard",
      "signal_category": "dry_powder",
      "summary": "J.C. Flowers VI L.P. filed Form D - private fund raising capital (fresh dry powder to deploy)",
      "excerpt": "SEC Form D, Item 3C private-fund exemption. Names the fund, not its portfolio deals.",
      "source_url": "https://www.sec.gov/Archives/edgar/data/2064377/000206437726000001/0002064377-26-000001-index.htm",
      "source_type": "sec-form-d",
      "source_date": "2026-07-21",
      "confidence": "high"
    },
    {
      "person_name": "Clarion Gables Multifamily Trust Parallel Fund, L.P.",
      "firm": "SEC Form D",
      "signal_type": "hard",
      "signal_category": "dry_powder",
      "summary": "Clarion Gables Multifamily Trust Parallel Fund, L.P. filed Form D - private fund raising capital (fresh dry powder to deploy)",
      "excerpt": "SEC Form D, Item 3C private-fund exemption. Names the fund, not its portfolio deals.",
      "source_url": "https://www.sec.gov/Archives/edgar/data/1712530/000171253026000004/0001712530-26-000004-index.htm",
      "source_type": "sec-form-d",
      "source_date": "2026-07-21",
      "confidence": "high"
    },
    {
      "person_name": "Sarissa Capital Domestic Fund LP",
      "firm": "SEC Form D",
      "signal_type": "hard",
      "signal_category": "dry_powder",
      "summary": "Sarissa Capital Domestic Fund LP filed Form D - private fund raising capital (fresh dry powder to deploy)",
      "excerpt": "SEC Form D, Item 3C private-fund exemption. Names the fund, not its portfolio deals.",
      "source_url": "https://www.sec.gov/Archives/edgar/data/1575277/000157527726000001/0001575277-26-000001-index.htm",
      "source_type": "sec-form-d",
      "source_date": "2026-07-21",
      "confidence": "high"
    },
    {
      "person_name": "Clarion Gables Multifamily Trust, L.P.",
      "firm": "SEC Form D",
      "signal_type": "hard",
      "signal_category": "dry_powder",
      "summary": "Clarion Gables Multifamily Trust, L.P. filed Form D - private fund raising capital (fresh dry powder to deploy)",
      "excerpt": "SEC Form D, Item 3C private-fund exemption. Names the fund, not its portfolio deals.",
      "source_url": "https://www.sec.gov/Archives/edgar/data/1635423/000163542326000004/0001635423-26-000004-index.htm",
      "source_type": "sec-form-d",
      "source_date": "2026-07-21",
      "confidence": "high"
    },
    {
      "person_name": "CDI Submersive Holdings, LP",
      "firm": "SEC Form D",
      "signal_type": "hard",
      "signal_category": "dry_powder",
      "summary": "CDI Submersive Holdings, LP filed Form D - private fund raising capital (fresh dry powder to deploy)",
      "excerpt": "SEC Form D, Item 3C private-fund exemption. Names the fund, not its portfolio deals.",
      "source_url": "https://www.sec.gov/Archives/edgar/data/2143859/000214385926000001/0002143859-26-000001-index.htm",
      "source_type": "sec-form-d",
      "source_date": "2026-07-21",
      "confidence": "high"
    },
    {
      "person_name": "Infinitas Capital SPV XXVI a series of Infinitas Capital Master LLC",
      "firm": "SEC Form D",
      "signal_type": "hard",
      "signal_category": "dry_powder",
      "summary": "Infinitas Capital SPV XXVI a series of Infinitas Capital Master LLC filed Form D - private fund raising capital (fresh dry powder to deploy)",
      "excerpt": "SEC Form D, Item 3C private-fund exemption. Names the fund, not its portfolio deals.",
      "source_url": "https://www.sec.gov/Archives/edgar/data/2099827/000209982726000008/0002099827-26-000008-index.htm",
      "source_type": "sec-form-d",
      "source_date": "2026-07-21",
      "confidence": "high"
    },
    {
      "person_name": "Volantis Series A, a series of Ten6 Ventures SPV, LLC",
      "firm": "SEC Form D",
      "signal_type": "hard",
      "signal_category": "dry_powder",
      "summary": "Volantis Series A, a series of Ten6 Ventures SPV, LLC filed Form D - private fund raising capital (fresh dry powder to deploy)",
      "excerpt": "SEC Form D, Item 3C private-fund exemption. Names the fund, not its portfolio deals.",
      "source_url": "https://www.sec.gov/Archives/edgar/data/2137050/000213705026000001/0002137050-26-000001-index.htm",
      "source_type": "sec-form-d",
      "source_date": "2026-07-21",
      "confidence": "high"
    },
    {
      "person_name": "Stone Temple Alternative Yield Fund (QP), a series of Stone Temple Investments LLC",
      "firm": "SEC Form D",
      "signal_type": "hard",
      "signal_category": "dry_powder",
      "summary": "Stone Temple Alternative Yield Fund (QP), a series of Stone Temple Investments LLC filed Form D - private fund raising capital (fresh dry powder to deploy)",
      "excerpt": "SEC Form D, Item 3C private-fund exemption. Names the fund, not its portfolio deals.",
      "source_url": "https://www.sec.gov/Archives/edgar/data/2141736/000214173626000002/0002141736-26-000002-index.htm",
      "source_type": "sec-form-d",
      "source_date": "2026-07-21",
      "confidence": "high"
    },
    {
      "person_name": "Inflection Ai 001 a series of Allocations 2026 Master, LLC",
      "firm": "SEC Form D",
      "signal_type": "hard",
      "signal_category": "dry_powder",
      "summary": "Inflection Ai 001 a series of Allocations 2026 Master, LLC filed Form D - private fund raising capital (fresh dry powder to deploy)",
      "excerpt": "SEC Form D, Item 3C private-fund exemption. Names the fund, not its portfolio deals.",
      "source_url": "https://www.sec.gov/Archives/edgar/data/2143545/000214354526000001/0002143545-26-000001-index.htm",
      "source_type": "sec-form-d",
      "source_date": "2026-07-21",
      "confidence": "high"
    },
    {
      "person_name": "RNN Ventures Panthalassa B Plus a series of Allocations 2026 Master, LLC",
      "firm": "SEC Form D",
      "signal_type": "hard",
      "signal_category": "dry_powder",
      "summary": "RNN Ventures Panthalassa B Plus a series of Allocations 2026 Master, LLC filed Form D - private fund raising capital (fresh dry powder to deploy)",
      "excerpt": "SEC Form D, Item 3C private-fund exemption. Names the fund, not its portfolio deals.",
      "source_url": "https://www.sec.gov/Archives/edgar/data/2145586/000214558626000001/0002145586-26-000001-index.htm",
      "source_type": "sec-form-d",
      "source_date": "2026-07-21",
      "confidence": "high"
    },
    {
      "person_name": "WAGMI 197 - WAGMI Master LLC",
      "firm": "SEC Form D",
      "signal_type": "hard",
      "signal_category": "dry_powder",
      "summary": "WAGMI 197 - WAGMI Master LLC filed Form D - private fund raising capital (fresh dry powder to deploy)",
      "excerpt": "SEC Form D, Item 3C private-fund exemption. Names the fund, not its portfolio deals.",
      "source_url": "https://www.sec.gov/Archives/edgar/data/2145597/000214559726000001/0002145597-26-000001-index.htm",
      "source_type": "sec-form-d",
      "source_date": "2026-07-21",
      "confidence": "high"
    },
    {
      "person_name": "P9A Opportunity BX a series of Allocations 2026 Master, LLC",
      "firm": "SEC Form D",
      "signal_type": "hard",
      "signal_category": "dry_powder",
      "summary": "P9A Opportunity BX a series of Allocations 2026 Master, LLC filed Form D - private fund raising capital (fresh dry powder to deploy)",
      "excerpt": "SEC Form D, Item 3C private-fund exemption. Names the fund, not its portfolio deals.",
      "source_url": "https://www.sec.gov/Archives/edgar/data/2143450/000214345026000001/0002143450-26-000001-index.htm",
      "source_type": "sec-form-d",
      "source_date": "2026-07-21",
      "confidence": "high"
    },
    {
      "person_name": "WCAS XV Co-Investors II LLC",
      "firm": "SEC Form D",
      "signal_type": "hard",
      "signal_category": "dry_powder",
      "summary": "WCAS XV Co-Investors II LLC filed Form D - private fund raising capital (fresh dry powder to deploy)",
      "excerpt": "SEC Form D, Item 3C private-fund exemption. Names the fund, not its portfolio deals.",
      "source_url": "https://www.sec.gov/Archives/edgar/data/2132802/000213280226000001/0002132802-26-000001-index.htm",
      "source_type": "sec-form-d",
      "source_date": "2026-07-21",
      "confidence": "high"
    },
    {
      "person_name": "CYPRESS CREEK PRIVATE STRATEGIES DOMESTIC FUND, L.P.",
      "firm": "SEC Form D",
      "signal_type": "hard",
      "signal_category": "dry_powder",
      "summary": "CYPRESS CREEK PRIVATE STRATEGIES DOMESTIC FUND, L.P. filed Form D - private fund raising capital (fresh dry powder to deploy)",
      "excerpt": "SEC Form D, Item 3C private-fund exemption. Names the fund, not its portfolio deals.",
      "source_url": "https://www.sec.gov/Archives/edgar/data/1228789/000122878926000001/0001228789-26-000001-index.htm",
      "source_type": "sec-form-d",
      "source_date": "2026-07-21",
      "confidence": "high"
    },
    {
      "person_name": "Fortis Private Strategies IV, LLC",
      "firm": "SEC Form D",
      "signal_type": "hard",
      "signal_category": "dry_powder",
      "summary": "Fortis Private Strategies IV, LLC filed Form D - private fund raising capital (fresh dry powder to deploy)",
      "excerpt": "SEC Form D, Item 3C private-fund exemption. Names the fund, not its portfolio deals.",
      "source_url": "https://www.sec.gov/Archives/edgar/data/2146047/000214604726000001/0002146047-26-000001-index.htm",
      "source_type": "sec-form-d",
      "source_date": "2026-07-21",
      "confidence": "high"
    },
    {
      "person_name": "ValueAct Strategic Global Partners IV, L.P.",
      "firm": "SEC Form D",
      "signal_type": "hard",
      "signal_category": "dry_powder",
      "summary": "ValueAct Strategic Global Partners IV, L.P. filed Form D - private fund raising capital (fresh dry powder to deploy)",
      "excerpt": "SEC Form D, Item 3C private-fund exemption. Names the fund, not its portfolio deals.",
      "source_url": "https://www.sec.gov/Archives/edgar/data/2141537/000214153726000001/0002141537-26-000001-index.htm",
      "source_type": "sec-form-d",
      "source_date": "2026-07-21",
      "confidence": "high"
    },
    {
      "person_name": "Landrock FL Condo Partnership, L.P.",
      "firm": "SEC Form D",
      "signal_type": "hard",
      "signal_category": "dry_powder",
      "summary": "Landrock FL Condo Partnership, L.P. filed Form D - private fund raising capital (fresh dry powder to deploy)",
      "excerpt": "SEC Form D, Item 3C private-fund exemption. Names the fund, not its portfolio deals.",
      "source_url": "https://www.sec.gov/Archives/edgar/data/2142323/000214232326000001/0002142323-26-000001-index.htm",
      "source_type": "sec-form-d",
      "source_date": "2026-07-21",
      "confidence": "high"
    },
    {
      "person_name": "Valor Venture Fund V, L.P.",
      "firm": "SEC Form D",
      "signal_type": "hard",
      "signal_category": "dry_powder",
      "summary": "Valor Venture Fund V, L.P. filed Form D - private fund raising capital (fresh dry powder to deploy)",
      "excerpt": "SEC Form D, Item 3C private-fund exemption. Names the fund, not its portfolio deals.",
      "source_url": "https://www.sec.gov/Archives/edgar/data/2027823/000202782326000001/0002027823-26-000001-index.htm",
      "source_type": "sec-form-d",
      "source_date": "2026-07-21",
      "confidence": "high"
    },
    {
      "person_name": "WCAS XV Co-Investors I LLC",
      "firm": "SEC Form D",
      "signal_type": "hard",
      "signal_category": "dry_powder",
      "summary": "WCAS XV Co-Investors I LLC filed Form D - private fund raising capital (fresh dry powder to deploy)",
      "excerpt": "SEC Form D, Item 3C private-fund exemption. Names the fund, not its portfolio deals.",
      "source_url": "https://www.sec.gov/Archives/edgar/data/2132831/000213283126000001/0002132831-26-000001-index.htm",
      "source_type": "sec-form-d",
      "source_date": "2026-07-21",
      "confidence": "high"
    },
    {
      "person_name": "FREX DB Series I DST",
      "firm": "SEC Form D",
      "signal_type": "hard",
      "signal_category": "dry_powder",
      "summary": "FREX DB Series I DST filed Form D - private fund raising capital (fresh dry powder to deploy)",
      "excerpt": "SEC Form D, Item 3C private-fund exemption. Names the fund, not its portfolio deals.",
      "source_url": "https://www.sec.gov/Archives/edgar/data/2126775/000212677526000004/0002126775-26-000004-index.htm",
      "source_type": "sec-form-d",
      "source_date": "2026-07-21",
      "confidence": "high"
    },
    {
      "person_name": "HSFP Fund LP",
      "firm": "SEC Form D",
      "signal_type": "hard",
      "signal_category": "dry_powder",
      "summary": "HSFP Fund LP filed Form D - private fund raising capital (fresh dry powder to deploy)",
      "excerpt": "SEC Form D, Item 3C private-fund exemption. Names the fund, not its portfolio deals.",
      "source_url": "https://www.sec.gov/Archives/edgar/data/2022438/000156611426000070/0001566114-26-000070-index.htm",
      "source_type": "sec-form-d",
      "source_date": "2026-07-21",
      "confidence": "high"
    },
    {
      "person_name": "HII Perplexity-09, a Series of HII Perplexity-B, LLC",
      "firm": "SEC Form D",
      "signal_type": "hard",
      "signal_category": "dry_powder",
      "summary": "HII Perplexity-09, a Series of HII Perplexity-B, LLC filed Form D - private fund raising capital (fresh dry powder to deploy)",
      "excerpt": "SEC Form D, Item 3C private-fund exemption. Names the fund, not its portfolio deals.",
      "source_url": "https://www.sec.gov/Archives/edgar/data/2146588/000214658826000001/0002146588-26-000001-index.htm",
      "source_type": "sec-form-d",
      "source_date": "2026-07-21",
      "confidence": "high"
    },
    {
      "person_name": "WCAS XV Feeder Fund, L.P.",
      "firm": "SEC Form D",
      "signal_type": "hard",
      "signal_category": "dry_powder",
      "summary": "WCAS XV Feeder Fund, L.P. filed Form D - private fund raising capital (fresh dry powder to deploy)",
      "excerpt": "SEC Form D, Item 3C private-fund exemption. Names the fund, not its portfolio deals.",
      "source_url": "https://www.sec.gov/Archives/edgar/data/2132843/000090445426000416/0000904454-26-000416-index.htm",
      "source_type": "sec-form-d",
      "source_date": "2026-07-21",
      "confidence": "high"
    },
    {
      "person_name": "WCAS XV, L.P.",
      "firm": "SEC Form D",
      "signal_type": "hard",
      "signal_category": "dry_powder",
      "summary": "WCAS XV, L.P. filed Form D - private fund raising capital (fresh dry powder to deploy)",
      "excerpt": "SEC Form D, Item 3C private-fund exemption. Names the fund, not its portfolio deals.",
      "source_url": "https://www.sec.gov/Archives/edgar/data/2124873/000090445426000416/0000904454-26-000416-index.htm",
      "source_type": "sec-form-d",
      "source_date": "2026-07-21",
      "confidence": "high"
    },
    {
      "person_name": "WCAS XV Lux, SCSp",
      "firm": "SEC Form D",
      "signal_type": "hard",
      "signal_category": "dry_powder",
      "summary": "WCAS XV Lux, SCSp filed Form D - private fund raising capital (fresh dry powder to deploy)",
      "excerpt": "SEC Form D, Item 3C private-fund exemption. Names the fund, not its portfolio deals.",
      "source_url": "https://www.sec.gov/Archives/edgar/data/2124872/000090445426000416/0000904454-26-000416-index.htm",
      "source_type": "sec-form-d",
      "source_date": "2026-07-21",
      "confidence": "high"
    },
    {
      "person_name": "Portola Springs Capital, LP",
      "firm": "SEC Form D",
      "signal_type": "hard",
      "signal_category": "dry_powder",
      "summary": "Portola Springs Capital, LP filed Form D - private fund raising capital (fresh dry powder to deploy)",
      "excerpt": "SEC Form D, Item 3C private-fund exemption. Names the fund, not its portfolio deals.",
      "source_url": "https://www.sec.gov/Archives/edgar/data/1717344/000171734426000002/0001717344-26-000002-index.htm",
      "source_type": "sec-form-d",
      "source_date": "2026-07-21",
      "confidence": "high"
    },
    {
      "person_name": "Blueprint 2025 Co-Invest 1, LLLP",
      "firm": "SEC Form D",
      "signal_type": "hard",
      "signal_category": "dry_powder",
      "summary": "Blueprint 2025 Co-Invest 1, LLLP filed Form D - private fund raising capital (fresh dry powder to deploy)",
      "excerpt": "SEC Form D, Item 3C private-fund exemption. Names the fund, not its portfolio deals.",
      "source_url": "https://www.sec.gov/Archives/edgar/data/2081752/000208175226000001/0002081752-26-000001-index.htm",
      "source_type": "sec-form-d",
      "source_date": "2026-07-21",
      "confidence": "high"
    },
    {
      "person_name": "Bloomfield Capital Fund IV, LP - Series E",
      "firm": "SEC Form D",
      "signal_type": "hard",
      "signal_category": "dry_powder",
      "summary": "Bloomfield Capital Fund IV, LP - Series E filed Form D - private fund raising capital (fresh dry powder to deploy)",
      "excerpt": "SEC Form D, Item 3C private-fund exemption. Names the fund, not its portfolio deals.",
      "source_url": "https://www.sec.gov/Archives/edgar/data/2076935/000101359426000752/0001013594-26-000752-index.htm",
      "source_type": "sec-form-d",
      "source_date": "2026-07-21",
      "confidence": "high"
    },
    {
      "person_name": "SOUTHERN AVENUE PARTNERS L P",
      "firm": "SEC Form D",
      "signal_type": "hard",
      "signal_category": "dry_powder",
      "summary": "SOUTHERN AVENUE PARTNERS L P filed Form D - private fund raising capital (fresh dry powder to deploy)",
      "excerpt": "SEC Form D, Item 3C private-fund exemption. Names the fund, not its portfolio deals.",
      "source_url": "https://www.sec.gov/Archives/edgar/data/1287821/000128782126000005/0001287821-26-000005-index.htm",
      "source_type": "sec-form-d",
      "source_date": "2026-07-21",
      "confidence": "high"
    },
    {
      "person_name": "Russian River Partners, LLC",
      "firm": "SEC Form D",
      "signal_type": "hard",
      "signal_category": "dry_powder",
      "summary": "Russian River Partners, LLC filed Form D - private fund raising capital (fresh dry powder to deploy)",
      "excerpt": "SEC Form D, Item 3C private-fund exemption. Names the fund, not its portfolio deals.",
      "source_url": "https://www.sec.gov/Archives/edgar/data/1613338/000101359426000751/0001013594-26-000751-index.htm",
      "source_type": "sec-form-d",
      "source_date": "2026-07-21",
      "confidence": "high"
    },
    {
      "person_name": "Blue Torch Credit Opportunities Structured Unlevered Rated Feeder Fund LP",
      "firm": "SEC Form D",
      "signal_type": "hard",
      "signal_category": "dry_powder",
      "summary": "Blue Torch Credit Opportunities Structured Unlevered Rated Feeder Fund LP filed Form D - private fund raising capital (fresh dry powder to deploy)",
      "excerpt": "SEC Form D, Item 3C private-fund exemption. Names the fund, not its portfolio deals.",
      "source_url": "https://www.sec.gov/Archives/edgar/data/2146545/000090514826003303/0000905148-26-003303-index.htm",
      "source_type": "sec-form-d",
      "source_date": "2026-07-21",
      "confidence": "high"
    }
  ]
}