{
  "last_run": "2026-07-22T22:58:51.914764",
  "feeds_checked": {
    "https://future.com/feed/": "2026-07-22T22:58:50.590560",
    "https://outofpocket.substack.com/feed": "2026-07-07T00:59:01.628975",
    "https://www.statnews.com/feed/": "2026-07-22T22:58:50.677174",
    "https://www.healthcaredive.com/feeds/news/": "2026-07-22T22:58:50.842056",
    "https://www.healthaffairs.org/action/showFeed?type=etoc&feed=rss&jc=hlthaff": "2026-07-11T07:49:34.896000",
    "https://www.medtechdive.com/feeds/news/": "2026-07-22T22:58:50.836670",
    "https://www.sequoiacap.com/feed/": "2026-07-22T22:58:50.825815",
    "https://hospitalogy.com/feed/": "2026-07-22T22:58:50.745956",
    "https://thehealthcareblog.com/feed/": "2026-07-22T22:58:50.885926",
    "https://www.mobihealthnews.com/feed": "2026-07-07T00:59:02.359957",
    "https://secondopinion.substack.com/feed": "2026-07-07T00:59:01.770990",
    "https://erictopol.substack.com/feed": "2026-07-07T00:59:01.699896",
    "https://www.venrock.com/feed/": "2026-07-22T22:58:50.624927",
    "https://www.digitalhealthwire.com/feed": "2026-07-22T22:58:51.469726",
    "https://www.thehealthcareblog.com/feed/": "2026-07-22T22:58:50.976135"
  },
  "signals_generated": 600
}