{
  "last_run": "2026-07-19T22:47:48.525408",
  "feeds_checked": {
    "https://chiefmartec.com/feed/": "2026-07-19T22:47:48.377887",
    "https://www.adexchanger.com/feed/": "2026-07-07T00:59:05.609195",
    "https://digiday.com/feed/": "2026-07-19T22:47:48.285066",
    "https://sparktoro.com/blog/feed/": "2026-07-19T22:47:48.189858",
    "https://www.socialmediatoday.com/feeds/news/": "2026-07-19T22:47:48.383079",
    "https://www.marketingdive.com/feeds/news/": "2026-07-19T22:47:48.332713",
    "https://searchengineland.com/feed": "2026-07-07T00:59:05.666940",
    "https://future.com/feed/": "2026-07-19T22:47:48.040823",
    "https://stratechery.com/feed/": "2026-07-19T22:47:48.272636",
    "https://www.lennysnewsletter.com/feed": "2026-07-19T22:47:48.177594",
    "https://2pml.com/feed/": "2026-07-19T22:47:48.328043",
    "https://www.adweek.com/feed/": "2026-07-19T22:47:48.289469",
    "https://andrewchen.com/feed/": "2026-07-19T22:47:48.484220",
    "https://www.forentrepreneurs.com/feed/": "2026-07-19T22:47:48.519413",
    "https://www.saastr.com/feed/": "2026-07-19T22:47:48.072715",
    "https://kylepoyar.substack.com/feed": "2026-07-07T00:59:05.733090",
    "https://mkt1.substack.com/feed": "2026-07-07T00:59:06.095710"
  },
  "signals_generated": 576
}