{
  "last_run": "2026-07-20T17:58:00.713887",
  "feeds_checked": {
    "https://esgnews.com/feed/": "2026-07-20T17:57:58.447152",
    "https://www.esgtoday.com/feed/": "2026-07-20T17:57:58.524843",
    "https://ssir.org/site/rss_2.0": "2026-07-20T17:57:58.722970",
    "https://www.pioneerspost.com/feed": "2026-07-20T17:57:58.631269",
    "https://impact-investor.com/feed/": "2026-07-20T17:57:58.639576",
    "https://impactalpha.com/feed/": "2026-07-07T19:50:22.011746",
    "https://www.takwinventures.com/feed/": "2026-07-20T17:57:59.353182",
    "https://www.bridgesfundmanagement.com/feed/": "2026-07-20T17:57:59.071523",
    "https://nextbillion.net/feed/": "2026-07-20T17:57:59.338887",
    "https://www.socialenterprise.org.uk/feed/": "2026-07-20T17:58:00.708693"
  },
  "signals_generated": 160
}