{
  "last_run": "2026-07-14T07:57:11.591373",
  "feeds_checked": {
    "https://techcrunch.com/category/climate/feed/": "2026-07-14T07:57:09.718508",
    "https://electrek.co/feed/": "2026-07-14T07:57:09.699729",
    "https://newsletter.mcj.vc/feed": "2026-07-14T07:57:09.991306",
    "https://cleantechnica.com/feed/": "2026-07-14T07:57:10.250476",
    "https://www.carbonbrief.org/feed/": "2026-07-14T07:57:10.818730",
    "https://www.canarymedia.com/feed": "2026-07-14T07:57:10.037522",
    "https://insideclimatenews.org/feed/": "2026-07-07T00:59:03.077666",
    "https://www.theclimatebrink.com/feed": "2026-07-14T07:57:10.533280",
    "https://heated.world/feed": "2026-07-14T07:57:10.162259",
    "https://grist.org/feed/": "2026-07-14T07:57:10.676179",
    "https://www.volts.wtf/feed": "2026-07-14T07:57:11.085282",
    "https://www.latitudemedia.com/feed": "2026-07-14T07:57:09.577740",
    "https://www.ctvc.co/feed": "2026-07-14T07:57:09.874717",
    "https://www.sustainabilitybynumbers.com/feed": "2026-07-07T00:59:03.356001",
    "https://www.lowercarbon.com/feed": "2026-07-14T07:57:11.135050",
    "https://www.watttime.org/feed": "2026-07-14T07:57:11.580941",
    "https://www.utilitydive.com/feeds/news/": "2026-07-14T07:57:10.539335",
    "https://www.canarymedia.com/rss.xml": "2026-07-14T07:57:10.576906",
    "https://www.distilled.earth/feed": "2026-07-14T07:57:10.353339",
    "https://climatedrift.substack.com/feed": "2026-07-07T00:59:02.872989",
    "https://climatepapa.substack.com/feed": "2026-07-07T00:59:03.500391"
  },
  "signals_generated": 713
}