{
  "last_run": "2026-07-13T02:26:58.839214",
  "feeds_checked": {
    "https://techcrunch.com/category/space/feed/": "2026-07-13T02:26:58.171871",
    "https://spacenews.com/feed/": "2026-07-13T02:26:58.160491",
    "https://spacecapital.substack.com/feed": "2026-07-07T00:59:06.817844",
    "https://feeds.arstechnica.com/arstechnica/science": "2026-07-13T02:26:58.237854",
    "https://www.universetoday.com/feed/": "2026-07-13T02:26:58.249076",
    "https://payloadspace.com/feed/": "2026-07-13T02:26:58.206700",
    "https://spaceambition.substack.com/feed": "2026-07-07T00:59:06.623412",
    "https://www.space.com/feeds/all": "2026-07-13T02:26:58.468045",
    "https://spacepolicyonline.com/feed/": "2026-07-12T23:50:48.555854",
    "https://www.nasaspaceflight.com/feed/": "2026-07-13T02:26:58.832561",
    "https://seraphim.vc/feed/": "2026-07-13T02:26:58.658384",
    "https://orbitalindex.com/feed.xml": "2026-07-13T02:26:58.077589",
    "https://spacedotbiz.substack.com/feed": "2026-07-07T00:59:06.702661",
    "https://payload.substack.com/feed": "2026-07-07T00:59:06.783083",
    "https://www.satellitetoday.com/feed/": "2026-07-07T00:59:06.519971",
    "https://foundersfund.com/feed/": "2026-07-13T02:26:58.732057",
    "https://europeanspaceflight.com/feed/": "2026-07-08T13:55:28.928037"
  },
  "signals_generated": 493
}