{
  "last_run": "2026-07-14T07:57:17.556324",
  "feeds_checked": {
    "https://techcrunch.com/category/space/feed/": "2026-07-14T07:57:15.928545",
    "https://spacenews.com/feed/": "2026-07-14T07:57:15.916749",
    "https://spacecapital.substack.com/feed": "2026-07-07T00:59:06.817844",
    "https://feeds.arstechnica.com/arstechnica/science": "2026-07-14T07:57:15.980142",
    "https://www.universetoday.com/feed/": "2026-07-14T07:57:16.464903",
    "https://payloadspace.com/feed/": "2026-07-14T07:57:16.243442",
    "https://spaceambition.substack.com/feed": "2026-07-07T00:59:06.623412",
    "https://www.space.com/feeds/all": "2026-07-14T07:57:16.440979",
    "https://spacepolicyonline.com/feed/": "2026-07-14T07:57:16.791130",
    "https://www.nasaspaceflight.com/feed/": "2026-07-14T07:57:16.595764",
    "https://seraphim.vc/feed/": "2026-07-14T07:57:16.632740",
    "https://orbitalindex.com/feed.xml": "2026-07-14T07:57:16.208702",
    "https://spacedotbiz.substack.com/feed": "2026-07-07T00:59:06.702661",
    "https://payload.substack.com/feed": "2026-07-07T00:59:06.783083",
    "https://www.satellitetoday.com/feed/": "2026-07-07T00:59:06.519971",
    "https://foundersfund.com/feed/": "2026-07-14T07:57:16.711589",
    "https://europeanspaceflight.com/feed/": "2026-07-14T07:57:17.549044"
  },
  "signals_generated": 539
}